pyreview/__init__.py
pyreview/access.py
pyreview/address.py
pyreview/assess.py
pyreview/config.py
pyreview/defaults.yml
ref/__init__.py
ref/access.py
ref/address.py
ref/assess.py
ref/config.py
ref/defaults.yml
ref/process.py
referia/__init__.py
referia/access.py
referia/address.py
referia/assess.py
referia/config.py
referia/defaults.yml
referia/display.py
referia/fake.py
referia/log.py
referia/system.py
referia/util.py
referia/widgets.py
referia-0.1.0.dist-info/METADATA
referia-0.1.0.dist-info/WHEEL
referia-0.1.0.dist-info/top_level.txt
referia-0.1.0.dist-info/RECORD
